odoo/addons/hr_employee_identification/README.rst
odoo/addons/hr_employee_identification/__init__.py
odoo/addons/hr_employee_identification/__manifest__.py
odoo/addons/hr_employee_identification/data/hr_employee_identification_type.xml
odoo/addons/hr_employee_identification/i18n/am.po
odoo/addons/hr_employee_identification/i18n/ar.po
odoo/addons/hr_employee_identification/i18n/bg.po
odoo/addons/hr_employee_identification/i18n/bs.po
odoo/addons/hr_employee_identification/i18n/ca.po
odoo/addons/hr_employee_identification/i18n/ca_ES.po
odoo/addons/hr_employee_identification/i18n/cs.po
odoo/addons/hr_employee_identification/i18n/da.po
odoo/addons/hr_employee_identification/i18n/de.po
odoo/addons/hr_employee_identification/i18n/el_GR.po
odoo/addons/hr_employee_identification/i18n/en_GB.po
odoo/addons/hr_employee_identification/i18n/es.po
odoo/addons/hr_employee_identification/i18n/es_AR.po
odoo/addons/hr_employee_identification/i18n/es_CL.po
odoo/addons/hr_employee_identification/i18n/es_CO.po
odoo/addons/hr_employee_identification/i18n/es_CR.po
odoo/addons/hr_employee_identification/i18n/es_DO.po
odoo/addons/hr_employee_identification/i18n/es_EC.po
odoo/addons/hr_employee_identification/i18n/es_ES.po
odoo/addons/hr_employee_identification/i18n/es_MX.po
odoo/addons/hr_employee_identification/i18n/es_PE.po
odoo/addons/hr_employee_identification/i18n/es_PY.po
odoo/addons/hr_employee_identification/i18n/es_VE.po
odoo/addons/hr_employee_identification/i18n/et.po
odoo/addons/hr_employee_identification/i18n/fa.po
odoo/addons/hr_employee_identification/i18n/fi.po
odoo/addons/hr_employee_identification/i18n/fr.po
odoo/addons/hr_employee_identification/i18n/fr_CA.po
odoo/addons/hr_employee_identification/i18n/fr_CH.po
odoo/addons/hr_employee_identification/i18n/gl.po
odoo/addons/hr_employee_identification/i18n/gl_ES.po
odoo/addons/hr_employee_identification/i18n/he.po
odoo/addons/hr_employee_identification/i18n/hr.po
odoo/addons/hr_employee_identification/i18n/hr_HR.po
odoo13_addon_hr_employee_identification-13.0.1.0.1.dev13.dist-info/METADATA
odoo13_addon_hr_employee_identification-13.0.1.0.1.dev13.dist-info/WHEEL
odoo13_addon_hr_employee_identification-13.0.1.0.1.dev13.dist-info/top_level.txt
odoo13_addon_hr_employee_identification-13.0.1.0.1.dev13.dist-info/RECORD
